oem/__init__.py
oem/base.py
oem/compare.py
oem/interface.py
oem/interp.py
oem/parsers.py
oem/tle.py
oem/tools.py
oem/components/__init__.py
oem/components/header.py
oem/components/metadata.py
oem/components/segment.py
oem/components/types.py
oem-0.4.1.dist-info/LICENSE
oem-0.4.1.dist-info/METADATA
oem-0.4.1.dist-info/WHEEL
oem-0.4.1.dist-info/top_level.txt
oem-0.4.1.dist-info/RECORD
