Metadata-Version: 2.1
Name: oem
Version: 0.4.1
Summary: Python Orbit Ephemeris Message (OEM) tools
Author-email: Brad Sease <bradsease@gmail.com>
License: MIT
Classifier: Development Status :: 4 - Beta
Classifier: Programming Language :: Python
Classifier: Programming Language :: Python :: 3
Classifier: Programming Language :: Python :: 3.8
Classifier: Programming Language :: Python :: 3.9
Classifier: Programming Language :: Python :: 3.10
Classifier: Programming Language :: Python :: 3.11
Classifier: Programming Language :: Python :: 3.12
Classifier: Programming Language :: Python :: 3 :: Only
Classifier: License :: OSI Approved :: MIT License
Classifier: Operating System :: OS Independent
Classifier: Topic :: Scientific/Engineering
Classifier: Topic :: Scientific/Engineering :: Astronomy
Requires-Python: >=3.8
License-File: LICENSE
Requires-Dist: numpy >=1.20
Requires-Dist: astropy >=5.0.8
Requires-Dist: lxml >=4.5.0
Requires-Dist: defusedxml >=0.6.0
Provides-Extra: coverage
Requires-Dist: pytest-cov ; extra == 'coverage'
Requires-Dist: coveralls ; extra == 'coverage'
Provides-Extra: test
Requires-Dist: pytest ; extra == 'test'
Requires-Dist: flake8 ; extra == 'test'
Provides-Extra: tle
Requires-Dist: sgp4 >=2.1 ; extra == 'tle'
